sipmarray/__init__.py
sipmarray/array.py
sipmarray/unit.py
sipmarray/models/Hdb_DigitalSiPM.py
sipmarray/models/S13370_3050.py
sipmarray/models/S13370_6050.py
sipmarray/models/S13370_6050CQ_02.py
sipmarray/models/S13370_6050VN.py
sipmarray/models/UZH_Tile.py
sipmarray/models/__init__.py
sipmarray/models/model_lib.py
sipmarray/scripts/__init__.py
sipmarray/scripts/script_sipmarray.py
sipmarray/scripts/script_sipmunit.py
sipmarray-1.2.dist-info/licenses/LICENSE
sipmarray-1.2.dist-info/METADATA
sipmarray-1.2.dist-info/WHEEL
sipmarray-1.2.dist-info/entry_points.txt
sipmarray-1.2.dist-info/top_level.txt
sipmarray-1.2.dist-info/RECORD
