Metadata-Version: 2.4
Name: sipmarray
Version: 1.2
Summary: A simple package to get the geometry of SiPM arrays.
Author-email: Ricardo Peres <r.motaperes@imperial.ac.uk>
Project-URL: Homepage, https://github.com/ricmperes/sipmarray
Project-URL: Bug Tracker, https://github.com/ricmperes/sipmarray/issues
Project-URL: Documentation, https://ricmperes.github.io/sipmarray/
Classifier: Programming Language :: Python :: 3
Classifier: License :: OSI Approved :: BSD License
Classifier: Operating System :: OS Independent
Classifier: Development Status :: 5 - Production/Stable
Classifier: Natural Language :: English
Classifier: Topic :: Scientific/Engineering :: Physics
Requires-Python: >=3.7
License-File: LICENSE
Requires-Dist: numpy
Requires-Dist: matplotlib
Requires-Dist: pandas
Dynamic: license-file
